{
  "game": "su15",
  "source": "abstract_model_vacuum_solver",
  "type": "analytical",
  "total_actions": 70,
  "max_level": 5,
  "per_level": {
    "L1": {
      "count": 8,
      "actions": [
        3471,
        3156,
        2778,
        2400,
        2085,
        1707,
        1329,
        1014
      ]
    },
    "L2": {
      "count": 17,
      "actions": [
        2478,
        2520,
        3606,
        3575,
        2471,
        2464,
        2462,
        3568,
        3562,
        3548,
        3554,
        3106,
        2784,
        2591,
        2275,
        2087,
        1832
      ]
    },
    "L3": {
      "count": 0,
      "actions": []
    },
    "L4": {
      "count": 0,
      "actions": []
    },
    "L5": {
      "count": 45,
      "actions": [
        1746,
        2406,
        2406,
        2406,
        2406,
        2406,
        2406,
        2406,
        2406,
        2406,
        2406,
        2406,
        2406,
        2406,
        2406,
        1783,
        2406,
        2406,
        2406,
        2406,
        2406,
        2406,
        2406,
        2406,
        2406,
        2406,
        2406,
        2406,
        2406,
        2406,
        1768,
        1768,
        1768,
        1768,
        1768,
        1768,
        1768,
        1768,
        1768,
        1768,
        1768,
        1768,
        1768,
        1768,
        1768
      ]
    },
    "L6": {
      "count": 0,
      "actions": []
    },
    "L7": {
      "count": 0,
      "actions": []
    },
    "L8": {
      "count": 0,
      "actions": []
    },
    "L9": {
      "count": 0,
      "actions": []
    }
  },
  "all_actions": [
    3471,
    3156,
    2778,
    2400,
    2085,
    1707,
    1329,
    1014,
    2478,
    2520,
    3606,
    3575,
    2471,
    2464,
    2462,
    3568,
    3562,
    3548,
    3554,
    3106,
    2784,
    2591,
    2275,
    2087,
    1832,
    1746,
    2406,
    2406,
    2406,
    2406,
    2406,
    2406,
    2406,
    2406,
    2406,
    2406,
    2406,
    2406,
    2406,
    2406,
    1783,
    2406,
    2406,
    2406,
    2406,
    2406,
    2406,
    2406,
    2406,
    2406,
    2406,
    2406,
    2406,
    2406,
    2406,
    1768,
    1768,
    1768,
    1768,
    1768,
    1768,
    1768,
    1768,
    1768,
    1768,
    1768,
    1768,
    1768,
    1768,
    1768
  ],
  "verified_levels": 2
}